dash_dynamic_images/__init__.py
dash_dynamic_images/_callback.py
dash_dynamic_images/_utils.py
dash_dynamic_images-1.0.1.dist-info/LICENSE
dash_dynamic_images-1.0.1.dist-info/METADATA
dash_dynamic_images-1.0.1.dist-info/WHEEL
dash_dynamic_images-1.0.1.dist-info/top_level.txt
dash_dynamic_images-1.0.1.dist-info/RECORD
