Metadata-Version: 2.1
Name: dash-dynamic-images
Version: 1.0.1
Summary: A library that helps with embedding dynamic and generative images into Plotly Dash applications.
Author-email: Tomasz Rewak <tomasz.rewak@gmail.com>
Project-URL: Homepage, https://github.com/TomaszRewak/dash-dynamic-images
Project-URL: Bug Tracker, https://github.com/TomaszRewak/dash-dynamic-images/issues
Classifier: Programming Language :: Python :: 3
Classifier: License :: OSI Approved :: MIT License
Classifier: Operating System :: OS Independent
Requires-Python: >=3.7
License-File: LICENSE
Requires-Dist: dash (<3,>=2.6.0)
Requires-Dist: Pillow (<10,>=9.5.0)
